pyd4all/__init__.py
pyd4all/api.py
pyd4all/cli/__init__.py
pyd4all/cli/async_typer.py
pyd4all/config.py
pyd4all/examples/__init__.py
pyd4all/examples/demo/README.md
pyd4all/examples/demo/__init__.py
pyd4all/examples/demo/app.py
pyd4all/examples/demo/auth.py
pyd4all/examples/demo/auth_user.py
pyd4all/examples/demo/cities.json
pyd4all/examples/demo/components_list.py
pyd4all/examples/demo/forms.py
pyd4all/examples/demo/routes/__init__.py
pyd4all/examples/demo/routes/api/__init__.py
pyd4all/examples/demo/routes/api/index.py
pyd4all/examples/demo/shared.py
pyd4all/examples/demo/sse.py
pyd4all/examples/demo/tables.py
pyd4all/examples/demo/tests.py
pyd4all/examples/demo/watcher_config.yaml
pyd4all/examples/faststream_in_memory.py
pyd4all/fluent/__init__.py
pyd4all/graph/__init__.py
pyd4all/graph/gqlalchemy_example.py
pyd4all/graph/sqlmodel_example.py
pyd4all/http/__init__.py
pyd4all/http/api/__init__.py
pyd4all/http/api/index.py
pyd4all/http/api/v1/__init__.py
pyd4all/http/api/v1/users/[user_id].py
pyd4all/http/api/v1/users/__init__.py
pyd4all/http/api/v1/users/index.py
pyd4all/http/hello/__init__.py
pyd4all/http/hello/world.py
pyd4all/main.py
pyd4all/scheduling/__init__.py
pyd4all/scheduling/aioclock_example.py
pyd4all/streamer.py
pyd4all/utils/__init__.py
pyd4all/utils/dir_tools.py
pyd4all/utils/routing_tools.py
pyd4all/utils/watcher_config.yaml
pyd4all/vector/__init__.py
pyd4all/vector/lance_example.py
pyd4all-2024.12.20.2.dist-info/METADATA
pyd4all-2024.12.20.2.dist-info/WHEEL
pyd4all-2024.12.20.2.dist-info/entry_points.txt
pyd4all-2024.12.20.2.dist-info/RECORD
